panda3d_astron/__init__.py
panda3d_astron/database.py
panda3d_astron/messenger.py
panda3d_astron/msgtypes.py
panda3d_astron/repository.py
panda3d_astron-1.1.0.dist-info/LICENSE
panda3d_astron-1.1.0.dist-info/METADATA
panda3d_astron-1.1.0.dist-info/WHEEL
panda3d_astron-1.1.0.dist-info/top_level.txt
panda3d_astron-1.1.0.dist-info/RECORD
